Workbook

Sheet Raw Orders (Messy)
B2: DAY 12 — WEEK 3 MINI-PROJECT | Raw Order Data (Messy — Do Not Edit)
B3: Problems: Missing order IDs · Mixed date formats · One price entered as text · Missing discounts · Blank region entries
B4: Order ID | C4: Order Date | D4: Customer Name | E4: Product Code | F4: Qty | G4: Unit Price (₹) | H4: Discount % | I4: Region
B5: ORD-001 | C5: 2025-01-03 | D5: Ravi Sharma | E5: EL-101 | F5: 5 | G5: 28500 | H5: 0.1 | I5: North
C6: 2025-01-05 | D6: Meena Pillai | E6: AP-204 | F6: 2 | G6: 4200 | H6: 0.05 | I6: South
B7: ORD-003 | C7: 2025-01-08 | D7: Karan Singh | E7: FW-312 | F7: 8 | G7: 2800 | H7: 0 | I7: West
B8: ORD-004 | C8: 2025-01-10 | D8: Divya Shah | E8: EL-205 | F8: 3 | G8: 62000 | H8: 0.15 | I8: North
B9: ORD-005 | C9: 15-Jan-2025 | D9: Saurabh Tiwari | E9: FT-101 | F9: 6 | G9: 1200 | H9: 0.05 | I9: East
B10: ORD-006 | C10: 2025-01-14 | D10: Pooja Mishra | E10: EL-101 | F10: 1 | G10: 28500 | H10: 0 | I10: South
B11: ORD-007 | C11: 2025-01-17 | D11: Amit Bhatt | E11: NT-401 | F11: 4 | G11: 2200 | H11: 0.1 | I11: West
B12: ORD-008 | C12: 2025-01-20 | D12: Anita Joshi | E12: AP-204 | F12: 3 | G12: 4200 | H12: 0.08 | I12: North
B13: ORD-009 | C13: 2025-01-22 | D13: Rohan Verma | E13: FW-312 | F13: 10 | G13: 2800 | H13: 0 | I13: East
B14: ORD-010 | C14: 2025-01-25 | D14: Priya Nair | E14: EL-205 | F14: 2 | G14: 62000 | H14: 0.12 | I14: South
B15: ORD-011 | C15: 2025-01-28 | D15: Vikram Das | E15: FT-101 | F15: 7 | G15: 1200 | H15: 0.05 | I15: West
B16: ORD-012 | C16: 2025-02-01 | D16: Sneha Iyer | E16: NT-401 | F16: 5 | G16: 2200 | H16: MISSING | I16: North
B17: ORD-013 | C17: 2025-02-04 | D17: Deepak Rao | E17: EL-101 | F17: 2 | G17: 28500 | H17: 0.1 | I17: East
B18: ORD-014 | C18: 2025-02-07 | D18: Nisha Kapoor | E18: AP-204 | F18: 9 | G18: 4200 | H18: 0.05 | I18: South
B19: ORD-015 | C19: 2025-02-10 | D19: Ravi Sharma | E19: FW-312 | F19: 4 | G19: 2800 | H19: 0
B20: ORD-016 | C20: 2025-02-13 | D20: Meena Pillai | E20: EL-205 | F20: 1 | G20: 62000 | H20: 0.15 | I20: North
B21: ORD-017 | C21: 04/02/2025 | D21: Karan Singh | E21: FT-101 | F21: 8 | G21: 1200 | H21: 0.05 | I21: West
B22: ORD-018 | C22: 2025-02-18 | E22: NT-401 | F22: 3 | G22: 2200 | H22: 0.1 | I22: South
B23: ORD-019 | C23: 2025-02-21 | D23: Pooja Mishra | E23: EL-101 | F23: 6 | G23: 28500 | H23: 0.08 | I23: East
B24: ORD-020 | C24: 2025-02-25 | D24: Amit Bhatt | E24: AP-204 | F24: 4 | G24: 4200 | H24: 0.05 | I24: West
B26: ISSUES FOUND IN THIS RAW DATA — Your job is to handle them in the Analysis sheet
B27: Row 6 | C27: Missing Order ID | D27: Assign ORD-002 manually
B28: Row 9 | C28: Order Date as text '15-Jan-2025' | D28: Treat as 15 Jan 2025 in your analysis
B29: Row 11 | C29: Unit Price entered as text '2800' | D29: Fix: convert to number — otherwise causes VALUE error in formulas
B30: Row 14 | C30: Discount % is blank/MISSING | D30: Assume 0% discount for this order
B31: Row 17 | C31: Missing Region | D31: Flag as 'Unknown' in clean data
B32: Row 19 | C32: Date format dd/mm/yyyy vs yyyy-mm-dd | D32: Standardise to yyyy-mm-dd
B33: Row 20 | C33: Missing Customer Name | D33: Flag as 'Unknown Customer'

Sheet Correct Sheet
A1: Order ID | B1: Order Date | C1: Customer Name | D1: Product Code | E1: Qty | F1: Unit Price (₹) | G1: Discount % | H1: Region
A2: ORD-001 | B2: 2025-01-03 | C2: Ravi Sharma | D2: EL-101 | E2: 5 | F2: 28500 | G2: 0.1 | H2: North
A3: ORD-002 | B3: 2025-01-05 | C3: Meena Pillai | D3: AP-204 | E3: 2 | F3: 4200 | G3: 0.05 | H3: South
A4: ORD-003 | B4: 2025-01-08 | C4: Karan Singh | D4: FW-312 | E4: 8 | F4: 2800 | G4: 0 | H4: West
A5: ORD-004 | B5: 2025-01-10 | C5: Divya Shah | D5: EL-205 | E5: 3 | F5: 62000 | G5: 0.15 | H5: North
A6: ORD-005 | B6: 45672 | C6: Saurabh Tiwari | D6: FT-101 | E6: 6 | F6: 1200 | G6: 0.05 | H6: East
A7: ORD-006 | B7: 2025-01-14 | C7: Pooja Mishra | D7: EL-101 | E7: 1 | F7: 28500 | G7: 0 | H7: South
A8: ORD-007 | B8: 2025-01-17 | C8: Amit Bhatt | D8: NT-401 | E8: 4 | F8: 2200 | G8: 0.1 | H8: West
A9: ORD-008 | B9: 2025-01-20 | C9: Anita Joshi | D9: AP-204 | E9: 3 | F9: 4200 | G9: 0.08 | H9: North
A10: ORD-009 | B10: 2025-01-22 | C10: Rohan Verma | D10: FW-312 | E10: 10 | F10: 2800 | G10: 0 | H10: East
A11: ORD-010 | B11: 2025-01-25 | C11: Priya Nair | D11: EL-205 | E11: 2 | F11: 62000 | G11: 0.12 | H11: South
A12: ORD-011 | B12: 2025-01-28 | C12: Vikram Das | D12: FT-101 | E12: 7 | F12: 1200 | G12: 0.05 | H12: West
A13: ORD-012 | B13: 2025-02-01 | C13: Sneha Iyer | D13: NT-401 | E13: 5 | F13: 2200 | G13: 0 | H13: North
A14: ORD-013 | B14: 2025-02-04 | C14: Deepak Rao | D14: EL-101 | E14: 2 | F14: 28500 | G14: 0.1 | H14: East
A15: ORD-014 | B15: 2025-02-07 | C15: Nisha Kapoor | D15: AP-204 | E15: 9 | F15: 4200 | G15: 0.05 | H15: South
A16: ORD-015 | B16: 2025-02-10 | C16: Ravi Sharma | D16: FW-312 | E16: 4 | F16: 2800 | G16: 0 | H16: Unknown
A17: ORD-016 | B17: 2025-02-13 | C17: Meena Pillai | D17: EL-205 | E17: 1 | F17: 62000 | G17: 0.15 | H17: North
A18: ORD-017 | B18: 45692 | C18: Karan Singh | D18: FT-101 | E18: 8 | F18: 1200 | G18: 0.05 | H18: West
A19: ORD-018 | B19: 2025-02-18 | C19: Unknown Customer | D19: NT-401 | E19: 3 | F19: 2200 | G19: 0.1 | H19: South
A20: ORD-019 | B20: 2025-02-21 | C20: Pooja Mishra | D20: EL-101 | E20: 6 | F20: 28500 | G20: 0.08 | H20: East
A21: ORD-020 | B21: 2025-02-25 | C21: Amit Bhatt | D21: AP-204 | E21: 4 | F21: 4200 | G21: 0.05 | H21: West

Sheet Product Catalogue
B2: PRODUCT CATALOGUE | XLOOKUP Source Table
B3: Use this sheet as your XLOOKUP source. Lookup key = Product Code (column B)
B4: Product Code | C4: Product Name | D4: Category | E4: Unit Price (₹) | F4: Cost Price (₹) | G4: Target Margin % | H4: Min Order Qty
B5: EL-101 | C5: Smart TV 55" | D5: Electronics | E5: 28500 | F5: 19000 | G5: 0.33 | H5: 1
B6: EL-205 | C6: Laptop Pro 14 | D6: Electronics | E6: 62000 | F6: 42000 | G6: 0.32 | H6: 1
B7: AP-204 | C7: Air Fryer XL | D7: Appliances | E7: 4200 | F7: 2600 | G7: 0.38 | H7: 2
B8: FW-312 | C8: Running Shoes M | D8: Footwear | E8: 2800 | F8: 1500 | G8: 0.46 | H8: 3
B9: FT-101 | C9: Yoga Mat Premium | D9: Fitness | E9: 1200 | F9: 550 | G9: 0.54 | H9: 5
B10: NT-401 | C10: Protein Powder 2kg | D10: Nutrition | E10: 2200 | F10: 1100 | G10: 0.5 | H10: 2
B13: XLOOKUP SYNTAX REMINDER
B14: Basic XLOOKUP | C14: XLOOKUP(lookup_value, lookup_array, return_array, [if_not_found]) | G14: Returns a single value from return_array
B15: In your Analysis sheet | C15: XLOOKUP(D5,'Product Catalogue'!$B$5:$B$10,'Product Catalogue'!$C$5:$C$10,"Unknown") | G15: D5 = Product Code in Analysis sheet
B16: For Cost Price | C16: XLOOKUP(D5,'Product Catalogue'!$B$5:$B$10,'Product Catalogue'!$F$5:$F$10,0) | G16: Change return array to column F (Cost Price)

Sheet Analysis (Your Work)
B2: DAY 12 — ANALYSIS SHEET | Week 3 Mini-Project | Build All Formulas Here
B3: Use XLOOKUP · IFS · Nested IF · Conditional Formatting — No hand-holding. You decide the approach.
B4: Order ID | C4: Customer Name | D4: Product Code | E4: Qty | F4: Product Name | G4: Unit Price (₹) | H4: Cost Price (₹) | I4: Disc % | J4: Revenue (₹) | K4: Profit (₹) | L4: Margin Tag | M4: Order Action
B5: ORD-001 | C5: Ravi Sharma | D5: EL-101 | E5: 5 | F5: =IFERROR(VLOOKUP(D5,'Product Catalogue'!$B$4:$C$10,2,0),"Not Found") -> Smart TV 55" | G5: =IFERROR(VLOOKUP(D5,'Product Catalogue'!$B$4:$E$10,4,0),"Not Found") -> 28500 | H5: =IFERROR(VLOOKUP(D5,'Product Catalogue'!$B$4:$F$10,5,0),"Not Found") -> 19000 | I5: 0.1 | J5: =E5*G5*(1-I5) -> 128250 | K5: =J5-E5*H5 -> 33250 | L5: =_xlfn.IFS(K5/J5>0.4,"High Margin",K5/J5>0.25,"Mid Margin",TRUE,"Low Margin") -> Mid Margin | M5: =IF(E5>=8,"Bulk-offer loyalty discount",IF(K5/J5>0.4,"Premium-upsell","Standard")) -> Standard
B6: ORD-002 | C6: Meena Pillai | D6: AP-204 | E6: 2 | F6: =IFERROR(VLOOKUP(D6,'Product Catalogue'!$B$4:$C$10,2,0),"Not Found") -> Air Fryer XL | G6: =IFERROR(VLOOKUP(D6,'Product Catalogue'!$B$4:$E$10,4,0),"Not Found") -> 4200 | H6: =IFERROR(VLOOKUP(D6,'Product Catalogue'!$B$4:$F$10,5,0),"Not Found") -> 2600 | I6: 0.05 | J6: =E6*G6*(1-I6) -> 7980 | K6: =J6-E6*H6 -> 2780 | L6: =_xlfn.IFS(K6/J6>0.4,"High Margin",K6/J6>0.25,"Mid Margin",TRUE,"Low Margin") -> Mid Margin | M6: =IF(E6>=8,"Bulk-offer loyalty discount",IF(K6/J6>0.4,"Premium-upsell","Standard")) -> Standard
B7: ORD-003 | C7: Karan Singh | D7: FW-312 | E7: 8 | F7: =IFERROR(VLOOKUP(D7,'Product Catalogue'!$B$4:$C$10,2,0),"Not Found") -> Running Shoes M | G7: =IFERROR(VLOOKUP(D7,'Product Catalogue'!$B$4:$E$10,4,0),"Not Found") -> 2800 | H7: =IFERROR(VLOOKUP(D7,'Product Catalogue'!$B$4:$F$10,5,0),"Not Found") -> 1500 | I7: 0 | J7: =E7*G7*(1-I7) -> 22400 | K7: =J7-E7*H7 -> 10400 | L7: =_xlfn.IFS(K7/J7>0.4,"High Margin",K7/J7>0.25,"Mid Margin",TRUE,"Low Margin") -> High Margin | M7: =IF(E7>=8,"Bulk-offer loyalty discount",IF(K7/J7>0.4,"Premium-upsell","Standard")) -> Bulk-offer loyalty discount
B8: ORD-004 | C8: Divya Shah | D8: EL-205 | E8: 3 | F8: =IFERROR(VLOOKUP(D8,'Product Catalogue'!$B$4:$C$10,2,0),"Not Found") -> Laptop Pro 14 | G8: =IFERROR(VLOOKUP(D8,'Product Catalogue'!$B$4:$E$10,4,0),"Not Found") -> 62000 | H8: =IFERROR(VLOOKUP(D8,'Product Catalogue'!$B$4:$F$10,5,0),"Not Found") -> 42000 | I8: 0.15 | J8: =E8*G8*(1-I8) -> 158100 | K8: =J8-E8*H8 -> 32100 | L8: =_xlfn.IFS(K8/J8>0.4,"High Margin",K8/J8>0.25,"Mid Margin",TRUE,"Low Margin") -> Low Margin | M8: =IF(E8>=8,"Bulk-offer loyalty discount",IF(K8/J8>0.4,"Premium-upsell","Standard")) -> Standard
B9: ORD-005 | C9: Saurabh Tiwari | D9: FT-101 | E9: 6 | F9: =IFERROR(VLOOKUP(D9,'Product Catalogue'!$B$4:$C$10,2,0),"Not Found") -> Yoga Mat Premium | G9: =IFERROR(VLOOKUP(D9,'Product Catalogue'!$B$4:$E$10,4,0),"Not Found") -> 1200 | H9: =IFERROR(VLOOKUP(D9,'Product Catalogue'!$B$4:$F$10,5,0),"Not Found") -> 550 | I9: 0.05 | J9: =E9*G9*(1-I9) -> 6840 | K9: =J9-E9*H9 -> 3540 | L9: =_xlfn.IFS(K9/J9>0.4,"High Margin",K9/J9>0.25,"Mid Margin",TRUE,"Low Margin") -> High Margin | M9: =IF(E9>=8,"Bulk-offer loyalty discount",IF(K9/J9>0.4,"Premium-upsell","Standard")) -> Premium-upsell
B10: ORD-006 | C10: Pooja Mishra | D10: EL-101 | E10: 1 | F10: =IFERROR(VLOOKUP(D10,'Product Catalogue'!$B$4:$C$10,2,0),"Not Found") -> Smart TV 55" | G10: =IFERROR(VLOOKUP(D10,'Product Catalogue'!$B$4:$E$10,4,0),"Not Found") -> 28500 | H10: =IFERROR(VLOOKUP(D10,'Product Catalogue'!$B$4:$F$10,5,0),"Not Found") -> 19000 | I10: 0 | J10: =E10*G10*(1-I10) -> 28500 | K10: =J10-E10*H10 -> 9500 | L10: =_xlfn.IFS(K10/J10>0.4,"High Margin",K10/J10>0.25,"Mid Margin",TRUE,"Low Margin") -> Mid Margin | M10: =IF(E10>=8,"Bulk-offer loyalty discount",IF(K10/J10>0.4,"Premium-upsell","Standard")) -> Standard
B11: ORD-007 | C11: Amit Bhatt | D11: NT-401 | E11: 4 | F11: =IFERROR(VLOOKUP(D11,'Product Catalogue'!$B$4:$C$10,2,0),"Not Found") -> Protein Powder 2kg | G11: =IFERROR(VLOOKUP(D11,'Product Catalogue'!$B$4:$E$10,4,0),"Not Found") -> 2200 | H11: =IFERROR(VLOOKUP(D11,'Product Catalogue'!$B$4:$F$10,5,0),"Not Found") -> 1100 | I11: 0.1 | J11: =E11*G11*(1-I11) -> 7920 | K11: =J11-E11*H11 -> 3520 | L11: =_xlfn.IFS(K11/J11>0.4,"High Margin",K11/J11>0.25,"Mid Margin",TRUE,"Low Margin") -> High Margin | M11: =IF(E11>=8,"Bulk-offer loyalty discount",IF(K11/J11>0.4,"Premium-upsell","Standard")) -> Premium-upsell
B12: ORD-008 | C12: Anita Joshi | D12: AP-204 | E12: 3 | F12: =IFERROR(VLOOKUP(D12,'Product Catalogue'!$B$4:$C$10,2,0),"Not Found") -> Air Fryer XL | G12: =IFERROR(VLOOKUP(D12,'Product Catalogue'!$B$4:$E$10,4,0),"Not Found") -> 4200 | H12: =IFERROR(VLOOKUP(D12,'Product Catalogue'!$B$4:$F$10,5,0),"Not Found") -> 2600 | I12: 0.08 | J12: =E12*G12*(1-I12) -> 11592 | K12: =J12-E12*H12 -> 3792 | L12: =_xlfn.IFS(K12/J12>0.4,"High Margin",K12/J12>0.25,"Mid Margin",TRUE,"Low Margin") -> Mid Margin | M12: =IF(E12>=8,"Bulk-offer loyalty discount",IF(K12/J12>0.4,"Premium-upsell","Standard")) -> Standard
B13: ORD-009 | C13: Rohan Verma | D13: FW-312 | E13: 10 | F13: =IFERROR(VLOOKUP(D13,'Product Catalogue'!$B$4:$C$10,2,0),"Not Found") -> Running Shoes M | G13: =IFERROR(VLOOKUP(D13,'Product Catalogue'!$B$4:$E$10,4,0),"Not Found") -> 2800 | H13: =IFERROR(VLOOKUP(D13,'Product Catalogue'!$B$4:$F$10,5,0),"Not Found") -> 1500 | I13: 0 | J13: =E13*G13*(1-I13) -> 28000 | K13: =J13-E13*H13 -> 13000 | L13: =_xlfn.IFS(K13/J13>0.4,"High Margin",K13/J13>0.25,"Mid Margin",TRUE,"Low Margin") -> High Margin | M13: =IF(E13>=8,"Bulk-offer loyalty discount",IF(K13/J13>0.4,"Premium-upsell","Standard")) -> Bulk-offer loyalty discount
B14: ORD-010 | C14: Priya Nair | D14: EL-205 | E14: 2 | F14: =IFERROR(VLOOKUP(D14,'Product Catalogue'!$B$4:$C$10,2,0),"Not Found") -> Laptop Pro 14 | G14: =IFERROR(VLOOKUP(D14,'Product Catalogue'!$B$4:$E$10,4,0),"Not Found") -> 62000 | H14: =IFERROR(VLOOKUP(D14,'Product Catalogue'!$B$4:$F$10,5,0),"Not Found") -> 42000 | I14: 0.12 | J14: =E14*G14*(1-I14) -> 109120 | K14: =J14-E14*H14 -> 25120 | L14: =_xlfn.IFS(K14/J14>0.4,"High Margin",K14/J14>0.25,"Mid Margin",TRUE,"Low Margin") -> Low Margin | M14: =IF(E14>=8,"Bulk-offer loyalty discount",IF(K14/J14>0.4,"Premium-upsell","Standard")) -> Standard
B15: ORD-011 | C15: Vikram Das | D15: FT-101 | E15: 7 | F15: =IFERROR(VLOOKUP(D15,'Product Catalogue'!$B$4:$C$10,2,0),"Not Found") -> Yoga Mat Premium | G15: =IFERROR(VLOOKUP(D15,'Product Catalogue'!$B$4:$E$10,4,0),"Not Found") -> 1200 | H15: =IFERROR(VLOOKUP(D15,'Product Catalogue'!$B$4:$F$10,5,0),"Not Found") -> 550 | I15: 0.05 | J15: =E15*G15*(1-I15) -> 7980 | K15: =J15-E15*H15 -> 4130 | L15: =_xlfn.IFS(K15/J15>0.4,"High Margin",K15/J15>0.25,"Mid Margin",TRUE,"Low Margin") -> High Margin | M15: =IF(E15>=8,"Bulk-offer loyalty discount",IF(K15/J15>0.4,"Premium-upsell","Standard")) -> Premium-upsell
B16: ORD-012 | C16: Sneha Iyer | D16: NT-401 | E16: 5 | F16: =IFERROR(VLOOKUP(D16,'Product Catalogue'!$B$4:$C$10,2,0),"Not Found") -> Protein Powder 2kg | G16: =IFERROR(VLOOKUP(D16,'Product Catalogue'!$B$4:$E$10,4,0),"Not Found") -> 2200 | H16: =IFERROR(VLOOKUP(D16,'Product Catalogue'!$B$4:$F$10,5,0),"Not Found") -> 1100 | I16: 0 | J16: =E16*G16*(1-I16) -> 11000 | K16: =J16-E16*H16 -> 5500 | L16: =_xlfn.IFS(K16/J16>0.4,"High Margin",K16/J16>0.25,"Mid Margin",TRUE,"Low Margin") -> High Margin | M16: =IF(E16>=8,"Bulk-offer loyalty discount",IF(K16/J16>0.4,"Premium-upsell","Standard")) -> Premium-upsell
... B24: ORD-020 | C24: Amit Bhatt | D24: AP-204 | E24: 4 | F24: =IFERROR(VLOOKUP(D24,'Product Catalogue'!$B$4:$C$10,2,0),"Not Found") -> Air Fryer XL | G24: =IFERROR(VLOOKUP(D24,'Product Catalogue'!$B$4:$E$10,4,0),"Not Found") -> 4200 | H24: =IFERROR(VLOOKUP(D24,'Product Catalogue'!$B$4:$F$10,5,0),"Not Found") -> 2600 | I24: 0.05 | J24: =E24*G24*(1-I24) -> 15960 | K24: =J24-E24*H24 -> 5560 | L24: =_xlfn.IFS(K24/J24>0.4,"High Margin",K24/J24>0.25,"Mid Margin",TRUE,"Low Margin") -> Mid Margin | M24: =IF(E24>=8,"Bulk-offer loyalty discount",IF(K24/J24>0.4,"Premium-upsell","Standard")) -> Standard
B27: SUMMARY SECTION — Build these after completing the order table above
B28: Total Revenue (all orders) | I28: =SUM(J5:J24) -> 867132
B29: Total Profit (all orders) | I29: =SUM(K5:K24) -> 244582
B30: Average Discount Given | I30: =AVERAGE(I5:I24) -> 0.064
B31: Highest Single Order Revenue | I31: =MAX(J5:J24) -> 158100
B32: Orders Flagged High Margin | I32: =COUNTIF(L5:L24,"High Margin") -> 9
B33: Orders Flagged Low Margin | I33: =COUNTIF(L5:L24,"Low Margin") -> 3
B35: CLIENT SUMMARY — Write 3-5 sentences here after completing your analysis
B36: Laptop Pro 14 is your highest revenue product with Rs 319920 i.e 36.8% of your total revenue
B37: Divya Shah is your highest value customer
B38: 9 products are of high margin because most of them has 0-5% discount
B39: Based on performance data increase the stock of Laptop Pro 14 as it contribute 36.8% of total revenue.Additionaly prioritize the 9 high margin products and reduce the stock of low margin or those have heave discount to sell these items.
B40: Row 11 had Unit Price entered as text '2800' — this would have caused a #VALUE! error in the Revenue formula. I converted it to a number in the clean data, which allowed all 20 revenue calculations to work correctly

Sheet Scoring Guide
B2: DAY 12 — WEEK 3 MINI-PROJECT SCORING GUIDE | Total: 60 Points
B3: Task | C3: Skill Tested | D3: Success Criteria | E3: Points
B4: Data Cleaning | C4: Analyst Thinking | D4: Fixed Order ID, text price, missing discount (→ 0%), unknown customer, date formats. Clean data in Analysis sheet. | E4: 8
B5: XLOOKUP — Product Name | C5: XLOOKUP | D5: XLOOKUP(D5,'Product Catalogue'!$B$5:$B$10,'Product Catalogue'!$C$5:$C$10,"Unknown") in col f — all 20 rows correct. | E5: 10
B6: XLOOKUP — Unit & Cost Price | C6: XLOOKUP | D6: Columns G and H correctly pull Unit Price and Cost Price from Catalogue for all 20 orders. | E6: 8
B7: Revenue Formula | C7: Formula Logic | D7: =E5*G5*(1-I5) — Qty × Unit Price × (1 - Discount). All 20 rows correct. No hardcoded values. | E7: 8
B8: Profit Formula | C8: Formula Logic | D8: =J5-E5*H5 — Revenue minus total cost (Qty × Cost Price). Logical, clean formula. | E8: 6
B9: IFS — Margin Tag | C9: IFS | D9: IFS(K5/J5>=0.4,"High Margin",K5/J5>=0.25,"Mid Margin",TRUE(),"Low Margin") — tags all 20 rows correctly. | E9: 10
B10: Nested IF — Order Action | C10: Nested IF | D10: IF(E5>=8,"Bulk — offer loyalty discount",IF(K5/J5>=0.4,"Premium — upsell","Standard")) — logical, 3-tier. | E10: 6
B11: Conditional Formatting | C11: CF | D11: At least 2 CF rules applied: e.g. green row for High Margin, red for Low Margin OR colour scale on Revenue column. | E11: 4
B12: Client Summary | C12: Communication | D12: 5 questions answered in the summary box. Uses numbers, product names, business language. Not just 'product X is best'. | E12: 6
B13: BONUS: Summary COUNTIF formulas work correctly | C13: Formula | D13: COUNTIF counts for High/Low Margin are accurate. | E13: +2 Bonus
B14: TOTAL (excl. bonus) | E14: 60
B16: GRADING BANDS
B17: 54–60 + bonus | C17: Distinction | D17: Week 3 complete. Ready for Week 4 (Charts & Dashboards).
B18: 45–53 | C18: Pass | D18: Good work. Review IFS / CF rules before Week 4.
B19: 33–44 | C19: Needs Work | D19: Redo XLOOKUP and formula tasks. Resubmit before Week 4.
B20: 0–32 | C20: Re-attempt | D20: Re-read Days 9–11 concept notes and redo all tasks.
B22: WEEK 3 KEY TAKEAWAYS
B23: 1. XLOOKUP is VLOOKUP's replacement — it works left-to-right AND right-to-left, handles missing values cleanly.
B24: 2. IFS replaces deeply nested IF — when you have 3+ conditions, IFS is cleaner and easier to audit.
B25: 3. Nested IF is still essential for 2-tier logic (binary decisions) — don't overcomplicate with IFS for simple cases.
B26: 4. Conditional Formatting turns a table into a visual decision tool — formula-based rules are the most powerful.
B27: 5. Data cleaning is not optional — a wrong text price cell breaks every revenue formula downstream.
B28: INTERVIEW: 'Walk me through how you'd build a sales dashboard from scratch in Excel.' → This project is your answer.
