Workbook

Sheet ⭐ Start Here
A1: ⭐ DAY 4 — WEEK 1 FINAL PROJECT
A2: No step-by-step guide. You decide the approach. This is the jump from following to thinking.
A4: STEP 1 — Clean the Data
A5: Go to 'Raw Data (Messy)' sheet. Read ALL the ⚠ issue flags. Then go to 'Clean Data' sheet and build the cleaned version. Decide what to include, what to exclude, and document your decisions.
A9: STEP 2 — Analyse
A10: Go to 'Analysis Tasks' sheet. Complete Task A (Revenue by Product + % contribution) Task B (Revenue by Month) Task C (Revenue by Sales Rep + RANK) Task D (VLOOKUP to get Regional Manager names)
A14: STEP 3 — Write the Client Summary
A15: Go to 'Client Summary' sheet. Fill in all 5 sections using your analysis numbers. This is the deliverable you'd send to the shop owner. No bullet points allowed — write in full sentences.
A20: 📚 Skills you are allowed to use (Days 1–3 only)
A21: Day 1 | B21: SUM, AVERAGE, RANK | C21: Revenue totals, ranking products/reps
A22: Day 2 | B22: % Contribution formula, Pivot Table concept | C22: Which product dominates revenue
A23: Day 3 | B23: VLOOKUP across sheets | C23: Lookup regional manager from a separate table
A24: All days | B24: IF formula for tagging | C24: Flag top performer, needs review, stable
A27: When you're done: send the completed file back. I will review your cleaning decisions, your analysis numbers, and your client summary writing. This is your first complete analyst deliverable.

Sheet Raw Data (Messy)
A1: 🗂 Day 4 — Raw Sales Data | Messy Version
A2: This data was collected by 3 different staff members across 2 months. It has NOT been cleaned. Your job starts here.
A3: Order ID | B3: Customer Name | C3: City | D3: Product | E3: Units Sold | F3: Unit Price (₹) | G3: Month | H3: Sales Rep | I3: ⚠ Known Issues (read before cleaning)
A4: ORD-001 | B4: Rahul Sharma | C4: Mumbai | D4: Earphones | E4: 45 | F4: 399 | G4: January | H4: Priya
A5: ORD-002 | B5: Anjali Singh | C5: Delhi | D5: USB Cable | E5: 80 | F5: 99 | G5: January | H5: Ravi
A6: ORD-003 | B6: Deepak Verma | C6: Bangalore | D6: Mobile Cover | F6: 149 | G6: January | H6: Priya | I6: ⚠ Missing Units — decide: exclude or estimate?
A7: ORD-004 | B7: Neha Gupta | C7: Mumbai | D7: Screen Guard | E7: 60 | F7: 79 | G7: January | H7: Suresh | I7: ⚠ City in ALL CAPS — standardise to Title Case
A8: ORD-005 | B8: Arjun Mehta | C8: Chennai | D8: Phone Stand | E8: 25 | F8: 249 | G8: January | H8: Ravi | I8: ⚠ Units = 'N/A' — this is text, not a number. Exclude from analysis.
A9: ORD-006 | B9: Rahul Sharma | C9: Mumbai | D9: Earphones | E9: 30 | F9: 399 | G9: January | H9: Priya | I9: ⚠ Month entered as '1' instead of 'January' — fix before pivot
A10: ORD-007 | B10: Pooja Patel | C10: Ahmedabad | D10: USB Cable | E10: N/A | F10: 99 | G10: January | H10: Suresh
A11: ORD-008 | B11: Kiran Rao | C11: Hyderabad | D11: Mobile Cover | E11: 55 | F11: 149 | G11: January | H11: Ravi | I11: ⚠ City inconsistency — 'MUMBAI' should match 'Mumbai'
A12: ORD-009 | B12: Amit Kumar | C12: Delhi | D12: Earphones | E12: 70 | F12: 399 | G12: February | H12: Priya | I12: ⚠ Missing Units — same issue as Row 6
A13: ORD-010 | B13: Sunita Joshi | C13: Mumbai | D13: Screen Guard | E13: 40 | F13: 79 | G13: February | H13: Suresh | I13: ⚠ Price entered as '₹99' (text) — strip symbol, convert to number
A14: ORD-011 | B14: Rohit Das | C14: Kolkata | D14: Phone Stand | F14: 249 | G14: February | H14: Priya
A15: ORD-012 | B15: Vikram Nair | C15: Bangalore | D15: USB Cable | E15: 90 | F15: 99 | G15: February | H15: Ravi
A16: ORD-013 | B16: Anjali Singh | C16: Delhi | D16: Mobile Cover | E16: 35 | F16: 149 | G16: February | H16: Suresh | I16: ⚠ Zero units — real transaction? Or data entry error?
A17: ORD-014 | B17: Manoj Yadav | C17: Mumbai | D17: Earphones | E17: 50 | F17: 399 | G17: February | H17: Ravi
A18: ORD-015 | B18: Deepak Verma | C18: Bangalore | D18: Screen Guard | E18: 0 | F18: 79 | G18: February | H18: Priya
A19: ORD-016 | B19: Priya Shah | C19: Chennai | D19: USB Cable | E19: 65 | F19: 99 | G19: February | H19: Suresh | I19: ⚠ Missing Units again — pattern: Priya's rows have this issue
A20: ORD-017 | B20: Kiran Rao | C20: Hyderabad | D20: Phone Stand | E20: 20 | F20: 249 | G20: February | H20: Ravi | I20: ⚠ Month = 'unknown' — cannot use in time analysis. Flag it.
A21: ORD-018 | B21: Rahul sharma | C21: Mumbai | D21: Earphones | F21: 399 | G21: February | H21: Priya | I21: ⚠ Possible duplicate of ORD-012 — same city, product, units, rep
A22: ORD-019 | B22: Neha Gupta | C22: Mumbai | D22: Screen Guard | E22: 30 | F22: 79 | G22: unknown | H22: Suresh
A23: ORD-020 | B23: Vikram Nair | C23: Bangalore | D23: USB Cable | E23: 90 | F23: 99 | G23: February | H23: Ravi

Sheet Sheet1
A1: Month | B1: (All)
A3: Row Labels | B3: Sum of Revenue (₹)
A4: ORD-001 | B4: 0.12600442
A5: ORD-002 | B5: 0.055580898
A6: ORD-004 | B6: 0.033264325
A7: ORD-005 | B7: 0.043685743
A8: ORD-006 | B8: 0.084002947
A9: ORD-008 | B9: 0.05751079
A10: ORD-009 | B10: 0.19600688
A11: ORD-010 | B11: 0.022176217
A12: ORD-012 | B12: 0.06252851
A13: ORD-013 | B13: 0.036597775
A14: ORD-014 | B14: 0.14000491
A15: ORD-016 | B15: 0.045159479
... A18: Grand Total | B18: 1

Sheet Clean Data
A1: ✅ Step 1 — Cleaned Data | You create this
A2: Copy rows from Raw Data that are usable. Apply these cleaning rules:
A3: 1. Standardise City names → Title Case (Mumbai, Delhi, Bangalore, Chennai, Hyderabad, Ahmedabad, Kolkata)
A4: 2. Customer Name → Title Case (Rahul Sharma, not RAHUL SHARMA or rahul sharma). Remove trailing spaces.
A5: 3. Rows where Units = blank, 'N/A', or 0 → EXCLUDE. Note how many you dropped.
A6: 4. Month = '1' → replace with 'January'. Month = 'unknown' → EXCLUDE.
A7: 5. Price = '₹99' → remove ₹ symbol and store as number 99.
A8: 6. If a row looks like a duplicate (same customer + product + city + rep + units) → keep one, exclude other. Note it.
A9: Order ID | B9: Customer Name | C9: City | D9: Product | E9: Units Sold | F9: Unit Price (₹) | G9: Month | H9: Sales Rep | I9: Revenue (₹)
A10: ORD-001 | B10: Rahul Sharma | C10: Mumbai | D10: Earphones | E10: 45 | F10: 399 | G10: January | H10: Priya | I10: =E10*F10 -> 17955
A11: ORD-002 | B11: Anjali Singh | C11: Delhi | D11: USB Cable | E11: 80 | F11: 99 | G11: January | H11: Ravi | I11: =E11*F11 -> 7920
A12: ORD-004 | B12: Neha Gupta | C12: Mumbai | D12: Screen Guard | E12: 60 | F12: 79 | G12: January | H12: Suresh | I12: =E12*F12 -> 4740
A13: ORD-005 | B13: Arjun Mehta | C13: Chennai | D13: Phone Stand | E13: 25 | F13: 249 | G13: January | H13: Ravi | I13: =E13*F13 -> 6225
A14: ORD-006 | B14: Rahul Sharma | C14: Mumbai | D14: Earphones | E14: 30 | F14: 399 | G14: January | H14: Priya | I14: =E14*F14 -> 11970
A15: ORD-008 | B15: Kiran Rao | C15: Hyderabad | D15: Mobile Cover | E15: 55 | F15: 149 | G15: January | H15: Ravi | I15: =E15*F15 -> 8195
A16: ORD-009 | B16: Amit Kumar | C16: Delhi | D16: Earphones | E16: 70 | F16: 399 | G16: February | H16: Priya | I16: =E16*F16 -> 27930
A17: ORD-010 | B17: Sunita Joshi | C17: Mumbai | D17: Screen Guard | E17: 40 | F17: 79 | G17: February | H17: Suresh | I17: =E17*F17 -> 3160
A18: ORD-012 | B18: Vikram Nair | C18: Bangalore | D18: USB Cable | E18: 90 | F18: 99 | G18: February | H18: Ravi | I18: =E18*F18 -> 8910
A19: ORD-013 | B19: Anjali Singh | C19: Delhi | D19: Mobile Cover | E19: 35 | F19: 149 | G19: February | H19: Suresh | I19: =E19*F19 -> 5215
A20: ORD-014 | B20: Manoj Yadav | C20: Mumbai | D20: Earphones | E20: 50 | F20: 399 | G20: February | H20: Ravi | I20: =E20*F20 -> 19950
A21: ORD-016 | B21: Priya Shah | C21: Chennai | D21: USB Cable | E21: 65 | F21: 99 | G21: February | H21: Suresh | I21: =E21*F21 -> 6435
... A23: ORD-020 | B23: Vikram Nair | C23: Bangalore | D23: USB Cable | E23: 90 | F23: 99 | G23: February | H23: Ravi | I23: =E23*F23 -> 8910
A24: 💡 Revenue column = Units Sold × Unit Price (₹) — use a formula, not manual calculation
A26: Rows I Excluded & Why
A27: Order ID | B27: Reason for Exclusion | C27: Type of Problem
A28: ORD-003 | B28: Units Sold Missing | C28: Missing Value
A29: ORD-007 | B29: Units Sold Missing | C29: Missing Value
A30: ORD-011 | B30: Units Sold Missing | C30: Missing Value
A31: ORD-015 | B31: Unit Shows Zero | C31: Data Error or Real Transaction
A32: ORD-018 | B32: Units Sold Missing | C32: Missing Value
A33: ORD-019 | B33: Month is unknown | C33: Timeline issue

Sheet Analysis Tasks
A1: 📊 Step 2 — Analysis | Use only what you've learned in Days 1–3
A3: Task A: Revenue by Product (SUM) | (Day 1 skill)
A4: Product | B4: Total Revenue (₹) | C4: % of Total Revenue
A5: Earphones | B5: =SUM('Clean Data'!I10,'Clean Data'!I14,'Clean Data'!I20,'Clean Data'!I16) -> 77805 | C5: =(B5/$B$10)*100 -> 54.601916
A6: USB Cable | B6: =SUM('Clean Data'!I11,'Clean Data'!I18,'Clean Data'!I21,'Clean Data'!I23) -> 32175 | C6: =(B6/$B$10)*100 -> 22.57974
A7: Mobile Cover | B7: =SUM('Clean Data'!I15,'Clean Data'!I19) -> 13410 | C7: =(B7/$B$10)*100 -> 9.4108565
A8: Screen Guard | B8: =SUM('Clean Data'!I17,'Clean Data'!I12) -> 7900 | C8: =(B8/$B$10)*100 -> 5.5440542
A9: Phone Stand | B9: =SUM('Clean Data'!I13,'Clean Data'!I22) -> 11205 | C9: =(B9/$B$10)*100 -> 7.8634338
A10: GRAND TOTAL | B10: =SUM(B5:B9) -> 142495 | C10: =SUM(C5:C9) -> 100
A13: Task B: Revenue by Month (SUM) | (Day 1 + Day 2 skill)
A14: Month | B14: Total Revenue (₹) | C14: % of Total
A15: January | B15: =SUM('Clean Data'!I10:I15) -> 57005 | C15: =B15/$B$17*100 -> 40.004912
A16: February | B16: =SUM('Clean Data'!I16:I23) -> 85490 | C16: =B16/$B$17*100 -> 59.995088
A17: GRAND TOTAL | B17: =SUM(B15:B16) -> 142495 | C17: =SUM(C15:C16) -> 100
A20: Task C: Revenue by Sales Rep (SUM + RANK) | (Day 1 skill)
A21: Sales Rep | B21: Total Revenue (₹) | C21: Rank
A22: Priya | B22: =SUM('Clean Data'!I10,'Clean Data'!I14,'Clean Data'!I16) -> 57855 | C22: =RANK(B22,$B$22:$B$24,0) -> 2
A23: Ravi | B23: =SUM('Clean Data'!I11,'Clean Data'!I13,'Clean Data'!I15,'Clean Data'!I18,'Clean Data'!I20,'Clean Data'!I22,'Clean Data'!I23) -> 65090 | C23: =RANK(B23,$B$22:$B$24,0) -> 1
A24: Suresh | B24: =SUM('Clean Data'!I12,'Clean Data'!I17,'Clean Data'!I19,'Clean Data'!I21) -> 19550 | C24: =RANK(B24,$B$22:$B$24,0) -> 3
A27: Task D: Use VLOOKUP — Regional Manager Lookup | (Day 3 skill)
A28: The company has a separate lookup table (see 'Lookup Table' sheet). Use VLOOKUP to bring the Regional Manager's name into the table below.
A29: Sales Rep | B29: City | C29: Total Revenue (₹) | D29: Regional Manager (VLOOKUP)
A30: Priya | B30: Mumbai / Ahmedabad | C30: 57855 | D30: =VLOOKUP(A30,'Lookup Table'!$A$3:$B$5,2,FALSE) -> Ms. Kavitha Reddy
A31: Ravi | B31: Bangalore / Hyderabad / Kolkata | C31: 65090 | D31: =VLOOKUP(A31,'Lookup Table'!$A$3:$B$5,2,FALSE) -> Mr. Sanjay Mehta
A32: Suresh | B32: Delhi / Chennai | C32: 19550 | D32: =VLOOKUP(A32,'Lookup Table'!$A$3:$B$5,2,FALSE) -> Ms. Kavitha Reddy

Sheet Lookup Table
A1: Sales Rep → Regional Manager Lookup
A2: Sales Rep | B2: Regional Manager
A3: Priya | B3: Ms. Kavitha Reddy
A4: Ravi | B4: Mr. Sanjay Mehta
A5: Suresh | B5: Ms. Kavitha Reddy

Sheet Client Summary
A1: 📄 Step 3 — One-Page Client Summary | You write this
A3: CLIENT: [Write client name or 'Retail Shop Owner']
A4: REPORT PERIOD: January–February 2026 | Prepared by: Deepanshu
A6: 1. OVERVIEW — What does this data tell us?
A7: [Write 2–3 sentences. Total revenue earned. How many valid orders. Which months were covered. Example: 'The shop processed X valid orders across January and February, generating total revenue of ₹___. February showed higher activity than January.'].The shop processed 14 valid orders across January and February, generating total revenue of Rs.142495.February showed higher activity than January.
A11: 2. TOP PERFORMER — Which product drove the most revenue?
A12: [Name the product. Give its revenue and % contribution. Example: 'Earphones were the top revenue driver at ₹___ (___% of total revenue), despite ranking ___ in unit volume.']Earphones were the top revenue driver Rs77805(50.6% of total revenue)
A15: 3. LOW PERFORMER — Which product needs attention?
A16: [Name the product. Give its revenue and % contribution. Mention what the client should do. Example: 'Phone Stand contributed only ___% of revenue. The client should consider whether pricing or low awareness is the issue.'].Phone Stand contribute on 7.8% of revenue.You should consider whether price or awareness what should solve this problem
A19: 4. DATA QUALITY NOTE — What problems did you find?
A20: [This is important — clients trust analysts who flag issues. List: how many rows you excluded, why (missing data / text errors / duplicates), and what impact it had on the analysis. Example: 'X rows were excluded due to missing unit values, 1 duplicate order removed, and 1 row had an unreadable month value.']4 rows are excluded due to missing unit values and 1 row for unreadable month value.1 row is for showing 0 in unit value it is not clear whether it is real value or data error.
A24: 5. RECOMMENDATION — What should the client do next?
A25: [1 action per insight. Be specific. Example: • Focus stock investment on Earphones — highest revenue per unit, positive trend. • Investigate Phone Stand — low revenue despite decent price point. • Request Priya to correct data entry — 3 of her rows had missing unit values.']Focus stock investment in Earphones because they are at present you higher revenue product per unit it shows positive trend.Investigate Phone Stand for its low revenue despite its decent price.Request Priya and Suresh to correct their data entry 3 of the priya rows should shows missing unit values and 1 entry show 0 unit value and Suresh has 1 entry for missing unit value and 1 entry for unknown month timeline.
