Workbook

Sheet Product Catalogue
A1: Product Catalogue — ElectraMart India
A2: Master reference table | XLOOKUP pulls data from column A (Product ID), B (Name), C (Price)
A3: Product ID | B3: Product Name | C3: Unit Price (Rs) | D3: Category | E3: Stock Status | F3: Supplier | G3: Reorder Note
A4: PRD-001 | B4: Wireless Earphones | C4: 1299 | D4: Audio | E4: In Stock | F4: SoundTech | G4: Reorder at 50 units
A5: PRD-002 | B5: USB-C Cable 1m | C5: 199 | D5: Accessories | E5: In Stock | F5: CablePro | G5: Reorder at 100 units
A6: PRD-003 | B6: Phone Stand Adjustable | C6: 449 | D6: Accessories | E6: Low Stock | F6: DeskMate | G6: Order now — only 12 left
A7: PRD-004 | B7: Tempered Glass 6.1 | C7: 149 | D7: Protection | E7: In Stock | F7: ShieldTech | G7: Reorder at 150 units
A8: PRD-005 | B8: Bluetooth Speaker | C8: 2199 | D8: Audio | E8: Out of Stock | F8: SoundTech | G8: Awaiting next shipment
A9: PRD-006 | B9: Laptop Sleeve 15 | C9: 599 | D9: Bags | E9: In Stock | F9: CarryPlus | G9: Reorder at 30 units
A10: PRD-007 | B10: Wireless Mouse | C10: 1099 | D10: Computing | E10: In Stock | F10: ClickTech | G10: Reorder at 40 units
A11: PRD-008 | B11: Power Bank 10000mAh | C11: 1599 | D11: Charging | E11: Low Stock | F11: ChargePlus | G11: Order now — only 8 left
A12: PRD-009 | B12: Webcam 1080p | C12: 2499 | D12: Computing | E12: In Stock | F12: VisioTech | G12: Reorder at 20 units
A13: PRD-010 | B13: Mechanical Keyboard | C13: 3299 | D13: Computing | E13: Out of Stock | F13: KeyMaster | G13: Awaiting next shipment
A14: PRD-011 | B14: HDMI Cable 2m | C14: 249 | D14: Accessories | E14: In Stock | F14: CablePro | G14: Reorder at 80 units
A15: PRD-012 | B15: Phone Holder Car | C15: 349 | D15: Accessories | E15: In Stock | F15: DeskMate | G15: Reorder at 60 units

Sheet Sales Log
A1: Sales Log — March 2024 | Day 9 Practice Dataset
A2: Columns A-E = given data (do not edit). Columns F-J = YOUR formulas only. No hardcoding allowed.
A3: Order ID | B3: Date | C3: Product ID | D3: Qty Sold | E3: Sales Rep | F3: Product Name | G3: Unit Price (Rs) | H3: Total Revenue (Rs) | I3: Performance Tag | J3: Action Note
A4: ORD-301 | B4: 15-Mar-24 | C4: PRD-001 | D4: 3 | E4: Rohan Sharma | F4: =IFERROR(VLOOKUP(C4,'Product Catalogue'!A$4:C$15,2,0),"Not Found") -> Wireless Earphones | G4: =IFERROR(VLOOKUP(C4,'Product Catalogue'!A$4:C$15,3,0),0) -> 1299 | H4: =D4*G4 -> 3897 | I4: =IF(H4>5000,"High Value",IF(H4>2000,"Medium Value","Low Value")) -> Medium Value | J4: =IF(F4="Wireless Earphones","Flagship — protect margin",IF(G4>=2000,"Premium product — upsell opportunity","Standard item")) -> Flagship — protect margin
A5: ORD-302 | B5: 15-Mar-24 | C5: PRD-005 | D5: 1 | E5: Priya Mehta | F5: =IFERROR(VLOOKUP(C5,'Product Catalogue'!A$4:C$15,2,0),"Not Found") -> Bluetooth Speaker | G5: =IFERROR(VLOOKUP(C5,'Product Catalogue'!A$4:C$15,3,0),0) -> 2199 | H5: =D5*G5 -> 2199 | I5: =IF(H5>5000,"High Value",IF(H5>2000,"Medium Value","Low Value")) -> Medium Value | J5: =IF(F5="Wireless Earphones","Flagship — protect margin",IF(G5>=2000,"Premium product — upsell opportunity","Standard item")) -> Premium product — upsell opportunity
A6: ORD-303 | B6: 16-Mar-24 | C6: PRD-002 | D6: 10 | E6: Rohan Sharma | F6: =IFERROR(VLOOKUP(C6,'Product Catalogue'!A$4:C$15,2,0),"Not Found") -> USB-C Cable 1m | G6: =IFERROR(VLOOKUP(C6,'Product Catalogue'!A$4:C$15,3,0),0) -> 199 | H6: =D6*G6 -> 1990 | I6: =IF(H6>5000,"High Value",IF(H6>2000,"Medium Value","Low Value")) -> Low Value | J6: =IF(F6="Wireless Earphones","Flagship — protect margin",IF(G6>=2000,"Premium product — upsell opportunity","Standard item")) -> Standard item
A7: ORD-304 | B7: 16-Mar-24 | C7: PRD-008 | D7: 2 | E7: Anjali Singh | F7: =IFERROR(VLOOKUP(C7,'Product Catalogue'!A$4:C$15,2,0),"Not Found") -> Power Bank 10000mAh | G7: =IFERROR(VLOOKUP(C7,'Product Catalogue'!A$4:C$15,3,0),0) -> 1599 | H7: =D7*G7 -> 3198 | I7: =IF(H7>5000,"High Value",IF(H7>2000,"Medium Value","Low Value")) -> Medium Value | J7: =IF(F7="Wireless Earphones","Flagship — protect margin",IF(G7>=2000,"Premium product — upsell opportunity","Standard item")) -> Standard item
A8: ORD-305 | B8: 17-Mar-24 | C8: PRD-010 | D8: 1 | E8: Vikram Nair | F8: =IFERROR(VLOOKUP(C8,'Product Catalogue'!A$4:C$15,2,0),"Not Found") -> Mechanical Keyboard | G8: =IFERROR(VLOOKUP(C8,'Product Catalogue'!A$4:C$15,3,0),0) -> 3299 | H8: =D8*G8 -> 3299 | I8: =IF(H8>5000,"High Value",IF(H8>2000,"Medium Value","Low Value")) -> Medium Value | J8: =IF(F8="Wireless Earphones","Flagship — protect margin",IF(G8>=2000,"Premium product — upsell opportunity","Standard item")) -> Premium product — upsell opportunity
A9: ORD-306 | B9: 17-Mar-24 | C9: PRD-003 | D9: 5 | E9: Priya Mehta | F9: =IFERROR(VLOOKUP(C9,'Product Catalogue'!A$4:C$15,2,0),"Not Found") -> Phone Stand Adjustable | G9: =IFERROR(VLOOKUP(C9,'Product Catalogue'!A$4:C$15,3,0),0) -> 449 | H9: =D9*G9 -> 2245 | I9: =IF(H9>5000,"High Value",IF(H9>2000,"Medium Value","Low Value")) -> Medium Value | J9: =IF(F9="Wireless Earphones","Flagship — protect margin",IF(G9>=2000,"Premium product — upsell opportunity","Standard item")) -> Standard item
A10: ORD-307 | B10: 18-Mar-24 | C10: PRD-007 | D10: 4 | E10: Rohan Sharma | F10: =IFERROR(VLOOKUP(C10,'Product Catalogue'!A$4:C$15,2,0),"Not Found") -> Wireless Mouse | G10: =IFERROR(VLOOKUP(C10,'Product Catalogue'!A$4:C$15,3,0),0) -> 1099 | H10: =D10*G10 -> 4396 | I10: =IF(H10>5000,"High Value",IF(H10>2000,"Medium Value","Low Value")) -> Medium Value | J10: =IF(F10="Wireless Earphones","Flagship — protect margin",IF(G10>=2000,"Premium product — upsell opportunity","Standard item")) -> Standard item
A11: ORD-308 | B11: 18-Mar-24 | C11: PRD-004 | D11: 15 | E11: Anjali Singh | F11: =IFERROR(VLOOKUP(C11,'Product Catalogue'!A$4:C$15,2,0),"Not Found") -> Tempered Glass 6.1 | G11: =IFERROR(VLOOKUP(C11,'Product Catalogue'!A$4:C$15,3,0),0) -> 149 | H11: =D11*G11 -> 2235 | I11: =IF(H11>5000,"High Value",IF(H11>2000,"Medium Value","Low Value")) -> Medium Value | J11: =IF(F11="Wireless Earphones","Flagship — protect margin",IF(G11>=2000,"Premium product — upsell opportunity","Standard item")) -> Standard item
A12: ORD-309 | B12: 19-Mar-24 | C12: PRD-009 | D12: 2 | E12: Vikram Nair | F12: =IFERROR(VLOOKUP(C12,'Product Catalogue'!A$4:C$15,2,0),"Not Found") -> Webcam 1080p | G12: =IFERROR(VLOOKUP(C12,'Product Catalogue'!A$4:C$15,3,0),0) -> 2499 | H12: =D12*G12 -> 4998 | I12: =IF(H12>5000,"High Value",IF(H12>2000,"Medium Value","Low Value")) -> Medium Value | J12: =IF(F12="Wireless Earphones","Flagship — protect margin",IF(G12>=2000,"Premium product — upsell opportunity","Standard item")) -> Premium product — upsell opportunity
A13: ORD-310 | B13: 19-Mar-24 | C13: PRD-006 | D13: 3 | E13: Priya Mehta | F13: =IFERROR(VLOOKUP(C13,'Product Catalogue'!A$4:C$15,2,0),"Not Found") -> Laptop Sleeve 15 | G13: =IFERROR(VLOOKUP(C13,'Product Catalogue'!A$4:C$15,3,0),0) -> 599 | H13: =D13*G13 -> 1797 | I13: =IF(H13>5000,"High Value",IF(H13>2000,"Medium Value","Low Value")) -> Low Value | J13: =IF(F13="Wireless Earphones","Flagship — protect margin",IF(G13>=2000,"Premium product — upsell opportunity","Standard item")) -> Standard item
A14: ORD-311 | B14: 20-Mar-24 | C14: PRD-011 | D14: 20 | E14: Rohan Sharma | F14: =IFERROR(VLOOKUP(C14,'Product Catalogue'!A$4:C$15,2,0),"Not Found") -> HDMI Cable 2m | G14: =IFERROR(VLOOKUP(C14,'Product Catalogue'!A$4:C$15,3,0),0) -> 249 | H14: =D14*G14 -> 4980 | I14: =IF(H14>5000,"High Value",IF(H14>2000,"Medium Value","Low Value")) -> Medium Value | J14: =IF(F14="Wireless Earphones","Flagship — protect margin",IF(G14>=2000,"Premium product — upsell opportunity","Standard item")) -> Standard item
A15: ORD-312 | B15: 20-Mar-24 | C15: PRD-012 | D15: 7 | E15: Anjali Singh | F15: =IFERROR(VLOOKUP(C15,'Product Catalogue'!A$4:C$15,2,0),"Not Found") -> Phone Holder Car | G15: =IFERROR(VLOOKUP(C15,'Product Catalogue'!A$4:C$15,3,0),0) -> 349 | H15: =D15*G15 -> 2443 | I15: =IF(H15>5000,"High Value",IF(H15>2000,"Medium Value","Low Value")) -> Medium Value | J15: =IF(F15="Wireless Earphones","Flagship — protect margin",IF(G15>=2000,"Premium product — upsell opportunity","Standard item")) -> Standard item
... A18: ORD-315 | B18: 22-Mar-24 | C18: PRD-005 | D18: 2 | E18: Rohan Sharma | F18: =IFERROR(VLOOKUP(C18,'Product Catalogue'!A$4:C$15,2,0),"Not Found") -> Bluetooth Speaker | G18: =IFERROR(VLOOKUP(C18,'Product Catalogue'!A$4:C$15,3,0),0) -> 2199 | H18: =D18*G18 -> 4398 | I18: =IF(H18>5000,"High Value",IF(H18>2000,"Medium Value","Low Value")) -> Medium Value | J18: =IF(F18="Wireless Earphones","Flagship — protect margin",IF(G18>=2000,"Premium product — upsell opportunity","Standard item")) -> Premium product — upsell opportunity
A21: TASK GUIDE — Build these 5 formulas in columns F through J
A22: F4:F18 | B22: XLOOKUP | C22: Product Name | D22: =XLOOKUP(C4,'Product Catalogue'!A$4:A$15,'Product Catalogue'!B$4:B$15,"Not Found") -> #NAME?
A23: G4:G18 | B23: XLOOKUP | C23: Unit Price (Rs) | D23: =XLOOKUP(C4,'Product Catalogue'!A$4:A$15,'Product Catalogue'!C$4:C$15,0) -> #NAME?
A24: H4:H18 | B24: Formula | C24: Total Revenue (Rs) | D24: =G4*D4 #REF! -> #REF!
A25: I4:I18 | B25: IFS | C25: Performance Tag | D25: =_xludf.IFS(H4>=5000,"High Value",H4>=2000,"Medium Value",H4<2000,"Low Value") -> #NAME?
A26: J4:J18 | B26: Nested IF | C26: Action Note | D26: =IF(F4="Wireless Earphones","Flagship — protect margin",IF(G4>=2000,"Premium product — upsell opportunity","Standard item")) -> Flagship — protect margin

Sheet Concept Notes
A1: Day 9 Concept Notes — XLOOKUP vs VLOOKUP + Advanced IF Logic
A2: Term / Concept | B2: What it means | C2: Example (plain text — not a formula)
A3: ── XLOOKUP ──
A4: XLOOKUP syntax | B4: =XLOOKUP(lookup_value, lookup_array, return_array, if_not_found) -> #NAME? | C4: XLOOKUP(C4, A4:A15, B4:B15, Not Found)
A5: Why better than VLOOKUP | B5: VLOOKUP: lookup must be column 1, returns by col number (fragile). XLOOKUP: any column, direct range, never breaks on insert. | C5: VLOOKUP col_index=3 breaks if column inserted. XLOOKUP never does.
A6: if_not_found argument | B6: 4th argument — shows custom text instead of #N/A when no match found. | C6: XLOOKUP(C4, A:A, B:B, Product not found)
A7: Exact match | B7: 5th argument = 0 for exact match. Always use 0 for Product IDs. | C7: XLOOKUP(C4, A:A, B:B, Not Found, 0)
A8: ── IF LOGIC ──
A9: Simple IF | B9: Tests one condition. =IF(condition, value_if_true, value_if_false) | C9: IF(H4>=5000, High Value, Low Value)
A10: Nested IF | B10: Put another IF inside the false branch. Use for 2 conditions max — beyond that use IFS. | C10: IF(H4>=5000, High, IF(H4>=2000, Medium, Low))
A11: IFS function | B11: Cleaner than nested IF. Lists conditions top to bottom — first TRUE wins. Put most restrictive condition FIRST. | C11: IFS(H4>=5000, High Value, H4>=2000, Medium Value, H4<2000, Low Value)
A12: AND / OR in IF | B12: AND() = all conditions must be true. OR() = any one must be true. | C12: IF(AND(H4>=5000, D4>=3), Bulk High Value, Standard)
A13: ── VLOOKUP vs XLOOKUP ──
A14: Column restriction | B14: VLOOKUP: lookup must be leftmost column. XLOOKUP: lookup_array and return_array are separate — any columns. | C14: XLOOKUP can look up by column 3 and return column 1. VLOOKUP cannot.
A15: Column number fragility | B15: VLOOKUP col_index=3. Someone inserts a column — now returns wrong data with no error. | C15: XLOOKUP uses range references — inserting columns never changes the result.
A16: Error handling | B16: VLOOKUP returns #N/A — needs IFERROR() wrapper. XLOOKUP handles natively via 4th argument. | C16: IFERROR(VLOOKUP(...), Not found) vs XLOOKUP(..., Not found)
A17: When to use each | B17: XLOOKUP for all new work. VLOOKUP when maintaining old client files that already have it. | C17: Interview answer: I use XLOOKUP for new dashboards. I know VLOOKUP for legacy file maintenance.

Sheet Scoring Guide
A1: Day 9 Scoring Guide — Total: 40 points
A2: Task | B2: Points | C2: What is checked
A3: Col F — XLOOKUP Product Name | B3: 8 pts | C3: All 15 rows correct. Wireless Earphones for PRD-001, etc. -1pt per error.
A4: Col G — XLOOKUP Unit Price | B4: 8 pts | C4: All 15 prices correct. 1299 for PRD-001. Formula must use XLOOKUP, not hardcode.
A5: Col H — Total Revenue formula | B5: 6 pts
A6: Col I — IFS Performance Tag | B6: 8 pts | C6: High Value >= 5000, Medium Value >= 2000, Low Value < 2000. Exact text match required.
A7: Col J — Nested IF Action Note | B7: 6 pts | C7: Earphones = Flagship msg. Price >= 2000 = Premium msg. Others = Standard item.
A8: Written explanation (in chat) | B8: 4 pts | C8: Client-facing language. Describe what each column tells the business in plain English.
A10: PENALTY RULE: If Unit Price or Product Name values are hardcoded (typed manually instead of XLOOKUP formula), -4 points on that column even if the value is correct. The formula approach is the professional skill being tested.
A12: EXPECTED ANSWERS — check your work against these after submitting
A13: Order ID | B13: Product Name | C13: Unit Price | Revenue | Tag | Action
A14: ORD-301 | B14: Wireless Earphones | C14: Rs 1299 | Rs 3897 | Medium Value | Flagship — protect margin
A15: ORD-302 | B15: Bluetooth Speaker | C15: Rs 2199 | Rs 2199 | Medium Value | Premium product — upsell opportunity
A16: ORD-303 | B16: USB-C Cable 1m | C16: Rs 199 | Rs 1990 | Low Value | Standard item
A17: ORD-304 | B17: Power Bank 10000mAh | C17: Rs 1599 | Rs 3198 | Medium Value | Standard item
A18: ORD-305 | B18: Mechanical Keyboard | C18: Rs 3299 | Rs 3299 | Medium Value | Premium product — upsell opportunity
A19: ORD-306 | B19: Phone Stand Adjustable | C19: Rs 449 | Rs 2245 | Medium Value | Standard item
A20: ORD-307 | B20: Wireless Mouse | C20: Rs 1099 | Rs 4396 | Medium Value | Standard item
A21: ORD-308 | B21: Tempered Glass 6.1 | C21: Rs 149 | Rs 2235 | Medium Value | Standard item
A22: ORD-309 | B22: Webcam 1080p | C22: Rs 2499 | Rs 4998 | Medium Value | Premium product — upsell opportunity
A23: ORD-310 | B23: Laptop Sleeve 15 | C23: Rs 599 | Rs 1797 | Low Value | Standard item
A24: ORD-311 | B24: HDMI Cable 2m | C24: Rs 249 | Rs 4980 | Medium Value | Standard item
... A28: ORD-315 | B28: Bluetooth Speaker | C28: Rs 2199 | Rs 4398 | Medium Value | Premium product — upsell opportunity
